dj_snake/__init__.py
dj_snake/apps.py
dj_snake/management/__init__.py
dj_snake/management/commands/__init__.py
dj_snake/management/commands/djloaddata.py
dj_snake-1.1.2.dist-info/LICENSE
dj_snake-1.1.2.dist-info/METADATA
dj_snake-1.1.2.dist-info/WHEEL
dj_snake-1.1.2.dist-info/top_level.txt
dj_snake-1.1.2.dist-info/RECORD
