Metadata-Version: 2.1
Name: dj-snake
Version: 1.1.2
Summary: Django command to install the named fixture(s) in the database without overriding existing primary keys.
Home-page: https://github.com/mohi7solanki/dj-snake
Author: Mohit Solanki
Author-email: mohitsolanki619@gmail.com
License: MIT
Project-URL: Changelog, https://github.com/mohi7solanki/dj-snake/blob/main/HISTORY.rst
Project-URL: Twitter, https://twitter.com/mohi7solanki
Keywords: Django
Platform: UNKNOWN
Classifier: Development Status :: 5 - Production/Stable
Classifier: Framework :: Django :: 2.2
Classifier: Framework :: Django :: 3.0
Classifier: Framework :: Django :: 3.1
Classifier: Framework :: Django :: 3.2
Classifier: Framework :: Django :: 4.0
Classifier: Intended Audience :: Developers
Classifier: License :: OSI Approved :: MIT License
Classifier: Natural Language :: English
Classifier: Operating System :: OS Independent
Classifier: Programming Language :: Python :: 3 :: Only
Classifier: Programming Language :: Python :: 3
Classifier: Programming Language :: Python :: 3.6
Classifier: Programming Language :: Python :: 3.7
Classifier: Programming Language :: Python :: 3.8
Classifier: Programming Language :: Python :: 3.9
Classifier: Programming Language :: Python :: 3.10
Requires-Python: >=3.6
License-File: LICENSE
Requires-Dist: Django (>=2.2)
